oom_notifier/__init__.py
oom_notifier/__version__.py
oom_notifier/cli.py
oom_notifier/utils.py
oom_notifier-1.1.0.data/scripts/oom-notifier
oom_notifier-1.1.0.dist-info/LICENSE
oom_notifier-1.1.0.dist-info/METADATA
oom_notifier-1.1.0.dist-info/WHEEL
oom_notifier-1.1.0.dist-info/top_level.txt
oom_notifier-1.1.0.dist-info/RECORD
